sktlern/__init__.py
sktlern/mtplotlib.py
sktlern-0.2.dist-info/METADATA
sktlern-0.2.dist-info/WHEEL
sktlern-0.2.dist-info/top_level.txt
sktlern-0.2.dist-info/RECORD
