Metadata-Version: 2.1
Name: sktlern
Version: 0.2
Summary: sktlern
Author-email: gotkayasielkashy@gmail.com
Requires-Dist: g4f
